tradersbot
