Metadata-Version: 1.1
Name: tradersbot
Version: 0.2.4
Summary: Python wrapper for mangocore API
Home-page: https://github.com/traders/mangocore-client
Author: Traders@MIT
Author-email: traders@mit.edu
License: MIT
Download-URL: https://github.com/traders/mangocore-client/tarball/0.2.4
Keywords: MIT,quant,traders,trading
Platform: UNKNOWN
